README.rst
setup.py
date_machine/__init__.py
date_machine/cli.py
date_machine.egg-info/PKG-INFO
date_machine.egg-info/SOURCES.txt
date_machine.egg-info/dependency_links.txt
date_machine.egg-info/requires.txt
date_machine.egg-info/top_level.txt