Metadata-Version: 1.1
Name: date-machine
Version: 0.2
Summary: The last date parser
Home-page: http://asperous.github.io/date_machine
Author: Andy Chase
Author-email: andy@asperous.us
License: MIT
Download-URL: https://github.com/asperous/date_machine/archive/master.zip
Platform: UNKNOWN
Classifier: Development Status :: 4 - Beta
Classifier: Natural Language :: English
Classifier: License :: OSI Approved :: MIT License
Classifier: Programming Language :: Python
Classifier: Programming Language :: Python :: 2.7
Classifier: Topic :: Software Development :: Libraries :: Python Modules
Classifier: Topic :: Text Processing
